translatorai/__init__.py
translatorai/client.py
translatorai/utils/__init__.py
translatorai/utils/headers.py
translatorai-1.0.1.dist-info/METADATA
translatorai-1.0.1.dist-info/WHEEL
translatorai-1.0.1.dist-info/top_level.txt
translatorai-1.0.1.dist-info/RECORD
