Metadata-Version: 2.1
Name: translatorai
Version: 1.0.1
Summary: easy using AI, more texting models!
Home-page: https://github.com/RedPiarOfficial/AiTranslator
Author: Redpiar
Author-email: Regeonwix@gmail.com
License: UNKNOWN
Keywords: translation,translator,google,deepl,amazon,ai,libre
Platform: UNKNOWN
Classifier: Programming Language :: Python :: 3
Classifier: License :: OSI Approved :: MIT License
Classifier: Operating System :: OS Independent
Requires-Python: >=3.8
Requires-Dist: requests
